metrics_dash_backend_tools/__init__.py
metrics_dash_backend_tools/constants.py
metrics_dash_backend_tools/fetch_public_metrics.py
metrics_dash_backend_tools/graphs.py
metrics_dash_backend_tools/metrics_data_structures.py
metrics_dash_backend_tools/metrics_definitions.py
metrics_dash_backend_tools/oss_metric_entities.py
metrics_dash_backend_tools/reports.py
metrics_dash_backend_tools-0.1.5.dist-info/LICENSE
metrics_dash_backend_tools-0.1.5.dist-info/METADATA
metrics_dash_backend_tools-0.1.5.dist-info/WHEEL
metrics_dash_backend_tools-0.1.5.dist-info/RECORD
