Metadata-Version: 2.3
Name: metrics-dash-backend-tools
Version: 0.1.5
Summary: Backend tools for the DSACMS OSPO metrics dashboard
License: CC0
Author: Isaac Milarsky
Author-email: isaac.milarsky@hhs.cms.gov
Requires-Python: >=3.9,<4.0
Classifier: License :: Other/Proprietary License
Classifier: Programming Language :: Python :: 3
Classifier: Programming Language :: Python :: 3.9
Classifier: Programming Language :: Python :: 3.10
Classifier: Programming Language :: Python :: 3.11
Classifier: Programming Language :: Python :: 3.12
Classifier: Programming Language :: Python :: 3.13
Requires-Dist: pandas (>=2.2.3,<3.0.0)
Requires-Dist: pygal (>=3.0.5,<4.0.0)
Requires-Dist: requests (>=2.32.3,<3.0.0)
